{
  "name": "Cloud Composer Environment",
  "description": null,
  "pages": [
    {
      "name": "Cloud Composer Environment",
      "description": null,
      "widgets": [
        {
          "title": "Environment Healthy",
          "layout": {
            "column": 1,
            "row": 1,
            "width": 4,
            "height": 3
          },
          "linkedEntityGuids": null,
          "visualization": {
            "id": "viz.line"
          },
          "rawConfiguration": {
            "facet": {
              "showOtherSeries": false
            },
            "legend": {
              "enabled": true
            },
            "nrqlQueries": [
              {
                "accountIds": "{{accountIds}}",
                "query": "SELECT latest(`gcp.composer.environment.healthy`) FROM Metric WHERE entity.guid = '{{entity.id}}' TIMESERIES AUTO"
              }
            ],
            "platformOptions": {
              "ignoreTimeRange": false
            },
            "yAxisLeft": {
              "zero": true
            }
          }
        },
        {
          "title": "Active Celery Workers",
          "layout": {
            "column": 5,
            "row": 1,
            "width": 4,
            "height": 3
          },
          "linkedEntityGuids": null,
          "visualization": {
            "id": "viz.line"
          },
          "rawConfiguration": {
            "facet": {
              "showOtherSeries": false
            },
            "legend": {
              "enabled": true
            },
            "nrqlQueries": [
              {
                "accountIds": "{{accountIds}}",
                "query": "SELECT latest(`gcp.composer.environment.num_celery_workers`) FROM Metric WHERE entity.guid = '{{entity.id}}' TIMESERIES AUTO"
              }
            ],
            "platformOptions": {
              "ignoreTimeRange": false
            },
            "yAxisLeft": {
              "zero": true
            }
          }
        },
        {
          "title": "Active Schedulers",
          "layout": {
            "column": 9,
            "row": 1,
            "width": 4,
            "height": 3
          },
          "linkedEntityGuids": null,
          "visualization": {
            "id": "viz.line"
          },
          "rawConfiguration": {
            "facet": {
              "showOtherSeries": false
            },
            "legend": {
              "enabled": true
            },
            "nrqlQueries": [
              {
                "accountIds": "{{accountIds}}",
                "query": "SELECT latest(`gcp.composer.environment.active_schedulers`) FROM Metric WHERE entity.guid = '{{entity.id}}' TIMESERIES AUTO"
              }
            ],
            "platformOptions": {
              "ignoreTimeRange": false
            },
            "yAxisLeft": {
              "zero": true
            }
          }
        },
        {
          "title": "DAG Total Parse Time (s)",
          "layout": {
            "column": 1,
            "row": 4,
            "width": 4,
            "height": 3
          },
          "linkedEntityGuids": null,
          "visualization": {
            "id": "viz.line"
          },
          "rawConfiguration": {
            "facet": {
              "showOtherSeries": false
            },
            "legend": {
              "enabled": true
            },
            "nrqlQueries": [
              {
                "accountIds": "{{accountIds}}",
                "query": "SELECT average(`gcp.composer.environment.dag_processing.total_parse_time`) FROM Metric WHERE entity.guid = '{{entity.id}}' TIMESERIES AUTO"
              }
            ],
            "platformOptions": {
              "ignoreTimeRange": false
            },
            "yAxisLeft": {
              "zero": true
            }
          }
        }
      ]
    }
  ]
}